fds/__init__.py
fds/sdk/__init__.py
fds/sdk/FundsAPIforDigitalPortals/__init__.py
fds/sdk/FundsAPIforDigitalPortals/api_client.py
fds/sdk/FundsAPIforDigitalPortals/configuration.py
fds/sdk/FundsAPIforDigitalPortals/exceptions.py
fds/sdk/FundsAPIforDigitalPortals/model_utils.py
fds/sdk/FundsAPIforDigitalPortals/rest.py
fds/sdk/FundsAPIforDigitalPortals/api/__init__.py
fds/sdk/FundsAPIforDigitalPortals/api/fund_api.py
fds/sdk/FundsAPIforDigitalPortals/apis/__init__.py
fds/sdk/FundsAPIforDigitalPortals/model/__init__.py
fds/sdk/FundsAPIforDigitalPortals/model/attributes_member.py
fds/sdk/FundsAPIforDigitalPortals/model/cursor_based_pagination_output_object.py
fds/sdk/FundsAPIforDigitalPortals/model/cursor_based_pagination_output_object_without_total.py
fds/sdk/FundsAPIforDigitalPortals/model/error_meta_object.py
fds/sdk/FundsAPIforDigitalPortals/model/error_object.py
fds/sdk/FundsAPIforDigitalPortals/model/fund_issuer_search_data.py
fds/sdk/FundsAPIforDigitalPortals/model/fund_issuer_search_data_fund.py
fds/sdk/FundsAPIforDigitalPortals/model/fund_issuer_search_data_fund_domicile.py
fds/sdk/FundsAPIforDigitalPortals/model/fund_issuer_search_data_fund_domicile_exclude.py
fds/sdk/FundsAPIforDigitalPortals/model/fund_issuer_search_data_fund_domicile_restrict.py
fds/sdk/FundsAPIforDigitalPortals/model/fund_issuer_search_data_issuer.py
fds/sdk/FundsAPIforDigitalPortals/model/fund_issuer_search_data_issuer_country.py
fds/sdk/FundsAPIforDigitalPortals/model/fund_issuer_search_data_issuer_country_exclude.py
fds/sdk/FundsAPIforDigitalPortals/model/fund_issuer_search_data_issuer_country_restrict.py
fds/sdk/FundsAPIforDigitalPortals/model/fund_issuer_search_data_market.py
fds/sdk/FundsAPIforDigitalPortals/model/fund_issuer_search_data_market_exclude.py
fds/sdk/FundsAPIforDigitalPortals/model/fund_issuer_search_data_market_restrict.py
fds/sdk/FundsAPIforDigitalPortals/model/fund_issuer_search_data_share_class.py
fds.sdk.FundsAPIforDigitalPortals-0.10.0.dist-info/LICENSE
fds.sdk.FundsAPIforDigitalPortals-0.10.0.dist-info/METADATA
fds.sdk.FundsAPIforDigitalPortals-0.10.0.dist-info/WHEEL
fds.sdk.FundsAPIforDigitalPortals-0.10.0.dist-info/top_level.txt
fds.sdk.FundsAPIforDigitalPortals-0.10.0.dist-info/RECORD
